convertmusic/__init__.py
convertmusic/__main__.py
convertmusic-1.0.2.dist-info/entry_points.txt
convertmusic-1.0.2.dist-info/LICENSE
convertmusic-1.0.2.dist-info/WHEEL
convertmusic-1.0.2.dist-info/METADATA
convertmusic-1.0.2.dist-info/RECORD
