Metadata-Version: 2.1
Name: convertmusic
Version: 1.0.2
Summary: A simple music converter for local personal use
Keywords: music,conversion,ffmpeg
Author-email: "Taylor C. Richberger" <taywee@gmx.com>
Maintainer-email: "Taylor C. Richberger" <taywee@gmx.com>
Requires-Python: >=3.10
Classifier: Development Status :: 5 - Production/Stable
Classifier: Programming Language :: Python
Classifier: Programming Language :: Python :: 3.10
Classifier: Programming Language :: Python :: 3 :: Only
Classifier: Topic :: Multimedia :: Sound/Audio
Classifier: Topic :: Multimedia :: Sound/Audio :: Conversion
Classifier: Topic :: Utilities
Project-URL: repository, https://gitlab.com/Taywee/convertmusic
